xorq_hash_cache/__init__.py
xorq_hash_cache/hash_cache.py
xorq_hash_cache/dask_normalize/__init__.py
xorq_hash_cache/dask_normalize/_ctypes.py
xorq_hash_cache/dask_normalize/dask_normalize_function.py
xorq_hash_cache/dask_normalize/dask_normalize_other.py
xorq_hash_cache/dask_normalize/dask_normalize_utils.py
xorq_hash_cache/tests/test_hash_cache.py
xorq_hash_cache/utils/inspect_utils.py
xorq_hash_cache-0.1.0.dist-info/METADATA
xorq_hash_cache-0.1.0.dist-info/WHEEL
xorq_hash_cache-0.1.0.dist-info/RECORD
