Metadata-Version: 2.4
Name: xorq-hash-cache
Version: 0.1.0
Summary: python utility for caching function results
Requires-Python: >=3.10
Requires-Dist: attrs>=23.0
Requires-Dist: cloudpickle>=3.0
Requires-Dist: dask>=2025.1.0
Requires-Dist: pandas>=1.4
Requires-Dist: toolz>=0.10.0
Requires-Dist: urllib3>=2.2.3
